pytest_tornado/__init__.py
pytest_tornado/plugin.py
pytest_tornado_yen3-0.4.6.dist-info/DESCRIPTION.rst
pytest_tornado_yen3-0.4.6.dist-info/METADATA
pytest_tornado_yen3-0.4.6.dist-info/RECORD
pytest_tornado_yen3-0.4.6.dist-info/WHEEL
pytest_tornado_yen3-0.4.6.dist-info/entry_points.txt
pytest_tornado_yen3-0.4.6.dist-info/metadata.json
pytest_tornado_yen3-0.4.6.dist-info/top_level.txt
