Metadata-Version: 2.0
Name: pytest-tornado-yen3
Version: 0.4.6
Summary: A pytest plugin providing fixtures and markers to simplify testing of asynchronous tornado applications.
Home-page: https://github.com/eugeniy/pytest-tornado
Author: Eugeniy Kalinin, Yen3
Author-email: burump@gmail.com, yen3@gmail.com
License: Apache License, Version 2.0
Keywords: pytest pytest tornado async asynchronous testing unit tests plugin
Platform: UNKNOWN
Classifier: Development Status :: 5 - Production/Stable
Classifier: Environment :: Plugins
Classifier: Intended Audience :: Developers
Classifier: License :: OSI Approved :: Apache Software License
Classifier: Operating System :: OS Independent
Classifier: Programming Language :: Python
Classifier: Programming Language :: Python :: 2
Classifier: Programming Language :: Python :: 3
Classifier: Topic :: Software Development
Classifier: Topic :: Software Development :: Testing
Requires-Dist: pytest
Requires-Dist: tornado
